<Properties HasIOSDesignerOverlayBeenDismissed="True" StartupConfiguration="{B73008B4-4643-4442-A84D-4578836ED42B}|Default">
  <MonoDevelop.Ide.Workbench ActiveDocument="uber_uni/view_assets/chatView.cs">
    <Files>
      <File FileName="uber_uni/views_sideNav/sideNavViewPage.cs" Line="5" Column="32" IsPinned="True" />
      <File FileName="uber_uni/views_bottomNav/uberEatsView.cs" />
      <File FileName="uber_uni/views_sideNav/customTrip.cs" />
      <File FileName="uber_uni/RegisterAccountView.cs" />
      <File FileName="uber_uni/mainPagView.cs" />
      <File FileName="uber_uni/view_assets/orderRideView.cs" />
      <File FileName="uber_uni/RootViewController.cs" />
      <File FileName="uber_uni/AssemblyInfo.cs" />
      <File FileName="uber_uni.iOS/Main.cs" />
      <File FileName="uber_uni.iOS/AppDelegate.cs" />
      <File FileName="../../../../Library/Frameworks/Mono.framework/External/xbuild/Xamarin/Android/Xamarin.Android.Aapt2.targets" />
      <File FileName="../../.nuget/packages/xamarin.forms/5.0.0.1874/buildTransitive/Xamarin.Forms.targets" />
      <File FileName="uber_uni/views_bottomNav/uberGuardViews/trackCompnaionView.cs" />
      <File FileName="uber_uni/views_bottomNav/uberGuardViews/chatView.xaml.cs" />
      <File FileName="uber_uni/views_bottomNav/uberGuardViews/chatView.xaml" />
      <File FileName="uber_uni/views_bottomNav/uberGuardViews/inputBar.xaml.cs" />
      <File FileName="uber_uni/views_sideNav/travelHistoryView.cs" />
      <File FileName="../../../../Library/Frameworks/Mono.framework/External/xbuild/Xamarin/Android/Xamarin.Android.Common.targets" />
      <File FileName="../../.nuget/packages/xamarin.forms/5.0.0.1905/buildTransitive/Xamarin.Forms.targets" Line="201" Column="15" />
      <File FileName="uber_uni/obj/Debug/netstandard2.0/view_assets/inputBar.xaml.g.cs" />
      <File FileName="uber_uni/views_bottomNav/youView.cs" Line="36" Column="45" />
      <File FileName="uber_uni/view_assets/chatView.cs" Line="13" Column="69" />
    </Files>
    <Pads>
      <Pad Id="ProjectPad">
        <State name="__root__">
          <Node name="uber_uni" expanded="True">
            <Node name="uber_uni" expanded="True">
              <Node name="view_assets" expanded="True">
                <Node name="chatView.cs" selected="True" />
              </Node>
              <Node name="views_bottomNav" expanded="True" />
            </Node>
          </Node>
        </State>
      </Pad>
    </Pads>
  </MonoDevelop.Ide.Workbench>
  <MonoDevelop.Ide.ItemProperties.uber__uni.iOS PreferredExecutionTarget="MonoDevelop.IPhone.IPhoneSimulatorTarget.94DBE925-394C-4DD8-8694-643CD050AC37" />
  <MonoDevelop.Ide.DebuggingService.PinnedWatches />
  <MonoDevelop.Ide.Workspace ActiveConfiguration="Debug" />
  <MonoDevelop.Ide.DebuggingService.Breakpoints>
    <BreakpointStore />
  </MonoDevelop.Ide.DebuggingService.Breakpoints>
  <MultiItemStartupConfigurations />
  <MonoDevelop.Ide.ItemProperties.uber__uni.Android TriggeredFromHotReload="False" PreferredExecutionTarget="Android.Pixel_3a_API_29" />
</Properties>